data_Javharbek/__init__.py
data_Javharbek/airflow_dwh.py
data_Javharbek/clickhouse_dwh.py
data_Javharbek/my_module.py
data_Javharbek/my_module2.py
data_Javharbek/my_module3.py
data_Javharbek/my_module4.py
data_Javharbek/my_module5.py
data_Javharbek-0.56.dist-info/METADATA
data_Javharbek-0.56.dist-info/WHEEL
data_Javharbek-0.56.dist-info/top_level.txt
data_Javharbek-0.56.dist-info/RECORD
