Metadata-Version: 2.1
Name: data_Javharbek
Version: 0.56
Summary: DATA
Author: Javharbek
Author-email: jakharbek@gmail.com
Classifier: Programming Language :: Python :: 3
Classifier: License :: OSI Approved :: MIT License
Classifier: Operating System :: OS Independent
Requires-Python: >=3.6
